<http-page executeResourcesDynamically="false"
    forceEncodingForDynamicResources="false"
    name="/xRayControls/resources/sap/dfa/help/wpb/less/text_styles_default.css"
    playRequestsSequentially="false"
    recordedArtifactZipFileName="team/vus/@s@c02_@z@c1_@g@l_@account_@line_@items_@f@a@g@l@l03/%resources%/recorded-artifacts/d25f85bf-270f-47a6-8636-b474106f6663.zip"
    slaProfileEnabled="false" thinkTime="0"
    thinkTimeMode="MODE_SIMPLE_THINK_TIME" thinkTimeRangeEnd=""
    thinkTimeRangeStart="" uid="d25f85bf-270f-47a6-8636-b474106f6663">
    <embedded-action>cbb6f950-afe0-4a18-bfb0-40a694ae8842</embedded-action>
    <screenshotFileDescription>recorded-screenshots/sc_d7e4c5c1-bd3d-4b2d-9f72-0b124b5f861f.jpg</screenshotFileDescription>
</http-page>
<http-action actionType="1" contentType="text/css" enabled="false"
    extractorInjectPathPolicy="2" extractorPathPolicy="1"
    followRedirects="false" generatedByClient="false"
    lastModified="Mon, 11 Mar 2024 13:06:00 GMT"
    linkExtractorSeveralMatchOccurrence="1"
    linkExtractorSeveralMatchPolicy="1" linkExtractorType="6"
    method="GET"
    name="/xRayControls/resources/sap/dfa/help/wpb/less/text_styles_default.css"
    path="/xRayControls/resources/sap/dfa/help/wpb/less/text_styles_default.css"
    postType="6"
    recordedArtifactZipFileName="team/vus/@s@c02_@z@c1_@g@l_@account_@line_@items_@f@a@g@l@l03/%resources%/recorded-artifacts/d25f85bf-270f-47a6-8636-b474106f6663.zip"
    recordedResponseCode="200" responseSize="13688"
    serverUid="xray.hana.ondemand.com" slaProfileEnabled="false"
    uid="cbb6f950-afe0-4a18-bfb0-40a694ae8842" useKeepAlive="false">
    <responsePageFileDescription>recorded-responses/res_e6c35b56-9680-4736-8643-56b824f333c1.css</responsePageFileDescription>
    <requestContentFileDescription>recorded-requests/req_e6c35b56-9680-4736-8643-56b824f333c1.txt</requestContentFileDescription>
    <header name="Accept" value="text/css,*/*;q=0.1"/>
    <header name="Accept-Encoding" value="gzip, deflate, br"/>
    <header name="Accept-Language" value="en-US,en;q=0.9"/>
    <header name="Connection" value="keep-alive"/>
    <header name="Host" value="xray.hana.ondemand.com"/>
    <header name="Referer" value="https://ierp-zc1.pce.ibm.com:44391/"/>
    <header name="sec-ch-ua" value="&quot;Not_A Brand&quot;;v=&quot;8&quot;, &quot;Chromium&quot;;v=&quot;120&quot;, &quot;Google Chrome&quot;;v=&quot;120&quot;"/>
    <header name="sec-ch-ua-mobile" value="?0"/>
    <header name="sec-ch-ua-platform" value="&quot;Windows&quot;"/>
    <header name="Sec-Fetch-Dest" value="style"/>
    <header name="Sec-Fetch-Mode" value="no-cors"/>
    <header name="Sec-Fetch-Site" value="cross-site"/>
    <header name="User-Agent" value="Mozilla/5.0 (Windows NT 10.0; Win64; x64) AppleWebKit/537.36 (KHTML, like Gecko) Chrome/120.0.0.0 Safari/537.36"/>
    <responseHeaders>HTTP/1.1 200 &#xd;
Cache-Control: max-age=172800, public&#xd;
Last-Modified: Tue, 05 Dec 2023 13:05:38 GMT&#xd;
vary: accept-encoding&#xd;
Content-Encoding: gzip&#xd;
Content-Type: text/css&#xd;
Transfer-Encoding: chunked&#xd;
Date: Mon, 15 Jan 2024 14:22:08 GMT&#xd;
Keep-Alive: timeout=20&#xd;
Connection: keep-alive&#xd;
Server: SAP&#xd;
Strict-Transport-Security: max-age=31536000; includeSubDomains; preload</responseHeaders>
    <record-html-infos extractorRegExp="false" htmlType="0"/>
</http-action>
